last9/__init__.py
last9/wsgi/__init__.py
last9/wsgi/middleware.py
last9-0.2.1.dist-info/WHEEL
last9-0.2.1.dist-info/METADATA
last9-0.2.1.dist-info/RECORD
