Metadata-Version: 2.1
Name: last9
Version: 0.2.1
Summary: 
Author: Your Name
Author-email: you@example.com
Requires-Python: >=3.7,<4.0
Classifier: Programming Language :: Python :: 3
Classifier: Programming Language :: Python :: 3.7
Classifier: Programming Language :: Python :: 3.8
Classifier: Programming Language :: Python :: 3.9
Requires-Dist: Flask (>=1.1.2,<2.0.0)
Requires-Dist: Werkzeug (>=1.0.1,<2.0.0)
Requires-Dist: prometheus-client (>=0.11.0,<0.12.0)
